rap/__init__.py
rap/api_gateway/__init__.py
rap/api_gateway/app.py
rap/api_gateway/component.py
rap/api_gateway/route.py
rap/cli.py
rap/client/__init__.py
rap/client/core.py
rap/client/model.py
rap/client/processor/__init__.py
rap/client/processor/base.py
rap/client/processor/crypto.py
rap/client/processor/opentracing.py
rap/client/transport/__init__.py
rap/client/transport/channel.py
rap/client/transport/transport.py
rap/client/utils.py
rap/common/__init__.py
rap/common/channel.py
rap/common/conn.py
rap/common/crypto.py
rap/common/exceptions.py
rap/common/types.py
rap/common/utils.py
rap/server/__init__.py
rap/server/context.py
rap/server/core.py
rap/server/middleware/__init__.py
rap/server/middleware/base.py
rap/server/middleware/conn/__init__.py
rap/server/middleware/conn/block.py
rap/server/middleware/conn/conn_limit.py
rap/server/middleware/msg/__init__.py
rap/server/middleware/msg/access.py
rap/server/model.py
rap/server/processor/__init__.py
rap/server/processor/base.py
rap/server/processor/crypto.py
rap/server/processor/limit/__init__.py
rap/server/processor/limit/backend/__init__.py
rap/server/processor/limit/backend/base.py
rap/server/processor/limit/backend/redis.py
rap/server/processor/limit/core.py
rap/server/processor/limit/rule.py
rap/server/processor/limit/util.py
rap/server/processor/opentracing.py
rap/server/receiver.py
rap/server/registry.py
rap/server/sender.py
rap-0.5.3.8.dist-info/LICENSE
rap-0.5.3.8.dist-info/WHEEL
rap-0.5.3.8.dist-info/METADATA
rap-0.5.3.8.dist-info/RECORD
