Metadata-Version: 2.1
Name: rap
Version: 0.5.3.8
Summary: rap(par[::-1]) is advanced and fast python async rpc
Home-page: https://github.com/so1n/rap
License: Apache Software License
Author: So1n
Author-email: so1n897046026@gamil.com
Requires-Python: >=3.7,<4.0
Classifier: License :: Other/Proprietary License
Classifier: Programming Language :: Python :: 3
Classifier: Programming Language :: Python :: 3.7
Classifier: Programming Language :: Python :: 3.8
Classifier: Programming Language :: Python :: 3.9
Provides-Extra: api_gateway
Provides-Extra: crypto
Provides-Extra: opentracing
Provides-Extra: redis
Requires-Dist: aredis (>=1.1.8,<2.0.0); extra == "redis"
Requires-Dist: jaeger-client (>=4.4.0,<5.0.0); extra == "opentracing"
Requires-Dist: msgpack (>=1.0.0,<2.0.0)
Requires-Dist: opentracing (>=2.4.0,<3.0.0); extra == "opentracing"
Requires-Dist: pycrypto (==2.6.1); extra == "crypto"
Requires-Dist: starlette (>=0.14.2,<0.15.0); extra == "api_gateway"
Project-URL: Repository, https://github.com/so1n/rap
